hdl/data_mem.sv
// 4 KB memory 

module data_mem(clk, mem_write, mem_read, addr, write_data, funct3, read_data); 

parameter MEM_SIZE = 1024; 
parameter DATA_WIDTH = 32;

input logic clk;
input logic mem_write; 
input logic mem_read;
input logic [DATA_WIDTH-1:0] addr;
input logic [DATA_WIDTH-1:0] write_data;
input logic [2:0] funct3;
output logic [DATA_WIDTH-1:0] read_data;

logic [DATA_WIDTH-1:0] memory [0:1023]; // 1024 locations
logic [DATA_WIDTH-1:0] word; // temp: holds memory word before slicing


/* 
 * Writing code allows for writing data to a unique memory location given by bits [11:2] of the address, 1024 locations
 * Can write halves (upper and lower) to memory 
 * Can also write to specific byte lanes in memory (1) (2) (3) or (4), where each byte is a group of 8 bits 
 */

always @(posedge clk) begin 
    if (mem_write) begin
        case (funct3)
            3'b010: 
                memory[addr[11:2]] <= write_data;

            3'b001:
                if (addr[1])
                    memory[addr[11:2]][31:16] <= write_data[15:0];
                else 
                    memory[addr[11:2]][15:0] <= write_data[15:0];

            3'b000:
                case (addr[1:0])
                    2'b00: memory[addr[11:2]][7:0] <= write_data[7:0];
                    2'b01: memory[addr[11:2]][15:8] <= write_data[7:0];
                    2'b10: memory[addr[11:2]][23:16] <= write_data[7:0];
                    2'b11: memory[addr[11:2]][31:24] <= write_data[7:0];
                endcase
        endcase
    end
end

/* 
 * Reading is independent from the clock, no synchronization, always running 
 *
 * Code below allows for zero-extended OR sign-extended reading from upper and lower halves of the 32-bit data word
 * Code below allows for zero-extended OR sign-extended reading from 4 different bytes of the 32-bit data word 
 * Finally, can also just read the entire 32-bit data word 
 *
 * updated, 5/29/26 
 */ 

always @(*) begin
    word = memory[addr[11:2]]; // latch full word first; Icarus can't slice memory directly
    read_data = 32'b0;
    if (mem_read) begin
        case (funct3)
            3'b010:
                read_data = word;

            3'b001:
                if (addr[1])
                    read_data = {{16{word[31]}}, word[31:16]};
                else
                    read_data = {{16{word[15]}}, word[15:0]};

            3'b000:
                case (addr[1:0])
                    2'b00: read_data = {{24{word[7]}},  word[7:0]};
                    2'b01: read_data = {{24{word[15]}}, word[15:8]};
                    2'b10: read_data = {{24{word[23]}}, word[23:16]};
                    2'b11: read_data = {{24{word[31]}}, word[31:24]};
                endcase

            3'b101:
                if (addr[1])
                    read_data = {16'b0, word[31:16]};
                else
                    read_data = {16'b0, word[15:0]};

            3'b100:
                case (addr[1:0])
                    2'b00: read_data = {24'b0, word[7:0]};
                    2'b01: read_data = {24'b0, word[15:8]};
                    2'b10: read_data = {24'b0, word[23:16]};
                    2'b11: read_data = {24'b0, word[31:24]};
                endcase
        endcase
    end
end



endmodule

hdl/alu.sv
module alu(a, b, ALU_control, result, zero, overflow, lt, cout);

parameter data_width = 32; 

input [data_width-1:0] a, b; 
output reg [data_width-1:0] result; 
input [3:0] ALU_control;
output zero, overflow, lt, cout; // either 1 or 0 (true or false) for each 
reg carry; 


// use the funct3 for bits [2:0], eliminating the need for a second decoding stage for ALU operation selection 

localparam ADD = 4'b0000;
localparam SUB = 4'b1000;
localparam SLL = 4'b0001;
localparam SLT = 4'b0010;
localparam SLTU = 4'b0011;
localparam XOR = 4'b0100;
localparam SRL = 4'b0101;
localparam SRA = 4'b1101;
localparam OR = 4'b0110;
localparam AND = 4'b0111;


always @(*) begin
    result = 0;
    carry = 0;
    case(ALU_control) 
        ADD: {carry, result} = {1'b0, a} + {1'b0, b}; // zero-extend the a & b values to support 33-bit addition & make use of the carry bit 
        SUB: result = a - b;
        OR: result = a | b;
        AND: result = a & b;
        XOR: result = a ^ b;
        SLL: result = a << b[4:0]; // << point to the left indicate SL 
        SRL: result = a >> b[4:0];
        SRA: result = $signed(a) >>> b[4:0];
        SLTU: result = (a < b) ? 32'b1 : 32'b0;
        SLT: result = ($signed(a) < $signed(b)) ? 32'b1 : 32'b0; // returns true or false 
        default: result = 32'b0;
    endcase
end

assign zero = (result == 0); 
assign lt = ($signed(a) < $signed(b));
assign cout = carry; 


/* explaining my overflow logic 
 * 
 * take a[31] and b[31], which are the MSB of a and b and responsible for 
 * determining the sign of a and b. 
 * if a[31] == 0, then a is positive, else it's negative
 * if b[31] == 0, then b is positive, else it's negative
 * if a[31] == b[31], then that means that both a and b have the same sign
 * overflow occurs when adding/subtracting two numbers but being unable to 
 * express the correct result appropriately in the bitwidth provided, which
 * can occur here when adding two positive numbers and getting a negative value
 * fix: check if the MSB of the result is equal to the MSB of one of the data inputs
 * why?
 * case 1: add two positive numbers, get negative --> overflow 
 * case 2: add two negative numbers, get positive --> overflow 
 */ 

// 5/25/26 : updated overflow logic for SUB so that the SUB case was taken care of, which is pos - (neg) and neg - (pos) 
assign overflow = ((ALU_control == ADD) &&
    (a[31] == b[31]) &&
    (result[31] != a[31])) || ((ALU_control == SUB) && (a[31] != b[31]) && (result[31] != a[31]));

endmodule

hdl/reg_file.sv
module reg_file(clk, write_en, read_addr1, read_addr2, write_data, write_addr, reg1, reg2);

parameter depth = 32; // # of addressable locations in memory 
parameter width = 32; // word size, note: depth * width = capacity = 32b x 32b
parameter addr_bits = 5;

input [addr_bits-1:0] read_addr1, read_addr2, write_addr; // 5-bit addresses for 32 registers 
input [width-1:0] write_data; // one write port on RV32I register file 
input write_en, clk; // write enable and clock signal for synchronous write 
output [width-1:0] reg1, reg2; // two read ports on RV32I register file 

reg [width-1:0] reg_filex [depth-1:0];

integer i;
initial begin
    for (i = 0; i < depth; i = i + 1)
        reg_filex[i] = 0;
end

always @(posedge clk) // positive-edge triggered 
begin 
    if(write_en && write_addr != 0) // RISC-V architecture states x0 is hardwired to 0
        begin
        reg_filex[write_addr] <= write_data;
        end
end

assign reg1 = reg_filex[read_addr1]; 
assign reg2 = reg_filex[read_addr2];

endmodule

hdl/control_unit.sv
// Please refer to RISCV_CARD.pdf on my GitHub for more information about the instruction type formats

module control_unit (opcode, funct3, funct7, reg_write, alu_control, alu_src, alu_a_pc, lui, mem_read, mem_write, mem_to_reg, branch, jal, jalr, funct3_out);

input  logic [6:0] opcode;
input  logic [2:0] funct3;
input  logic [6:0] funct7;

output logic       reg_write;   // enable write to rd
output logic [3:0] alu_control; // operation select
output logic       alu_src;     // ALU B operand
output logic       alu_a_pc;    // ALU A operand
output logic       lui;         // LUI: bypass ALU, write imm directly to rd
output logic       mem_read;    // data memory read enable (loads)
output logic       mem_write;   // data memory write enable (stores)
output logic [1:0] mem_to_reg;  // writeback mux: 00=ALU result, 01=mem data, 10=PC+4
output logic       branch;      // B-type: datapath resolves condition using funct3_out + ALU flags
output logic       jal;         // JAL:  rd=PC+4, PC=PC+imm
output logic       jalr;        // JALR: rd=PC+4, PC=rs1+imm
output logic [2:0] funct3_out;  // passed to datapath for branch condition and memory access width

localparam [3:0] ALU_ADD  = 4'b0000;
localparam [3:0] ALU_SUB  = 4'b1000;
localparam [3:0] ALU_SLT  = 4'b0010;
localparam [3:0] ALU_SLTU = 4'b0011;

// RV32I opcodes 
localparam [6:0] OP       = 7'b0110011; // R: ADD SUB XOR OR AND SLL SRL SRA SLT SLTU
localparam [6:0] OP_IMM   = 7'b0010011; // I: ADDI XORI ORI ANDI SLLI SRLI SRAI SLTI SLTIU
localparam [6:0] LOAD     = 7'b0000011; // I: LB LH LW LBU LHU
localparam [6:0] JALR_OP  = 7'b1100111; // I: JALR
localparam [6:0] SYSTEM   = 7'b1110011; // I: ECALL EBREAK
localparam [6:0] STORE    = 7'b0100011; // S: SB SH SW
localparam [6:0] BRANCH   = 7'b1100011; // B: BEQ BNE BLT BGE BLTU BGEU
localparam [6:0] LUI_OP   = 7'b0110111; // U: LUI
localparam [6:0] AUIPC_OP = 7'b0010111; // U: AUIPC
localparam [6:0] JAL_OP   = 7'b1101111; // J: JAL

// Branch -> ALU comparison mapping 
function automatic [3:0] branch_alu_ctrl(input logic [2:0] f3);
    case (f3)
        3'b000, 3'b001: branch_alu_ctrl = ALU_SUB;  // BEQ, BNE
        3'b100, 3'b101: branch_alu_ctrl = ALU_SLT;  // BLT, BGE
        3'b110, 3'b111: branch_alu_ctrl = ALU_SLTU; // BLTU, BGEU
        default:        branch_alu_ctrl = ALU_SUB;
    endcase
endfunction

// Control signal selection 
always @(*) begin
    // Safe defaults: no-op, no memory access, no writeback
    reg_write   = 1'b0;
    alu_control = ALU_ADD;
    alu_src     = 1'b0;
    alu_a_pc    = 1'b0;
    lui         = 1'b0;
    mem_read    = 1'b0;
    mem_write   = 1'b0;
    mem_to_reg  = 2'b00;
    branch      = 1'b0;
    jal         = 1'b0;
    jalr        = 1'b0;
    funct3_out  = funct3;

    case (opcode)

        OP: begin // R-type
            reg_write = 1'b1;
            // funct7[5] distinguishes ADD/SUB and SRL/SRA: encoding directly matches ALU localparams
            alu_control = {funct7[5], funct3};
        end

        OP_IMM: begin // I-type arithmetic
            reg_write = 1'b1;
            alu_src = 1'b1;
            // inst[30] (funct7[5]) is an immediate bit for all I-type except SRLI/SRAI (funct3=101)
            // only gate it through for the shift-right case to avoid treating a negative
            // immediate as a SUB or SRA incorrectly
            alu_control = {funct7[5] & (funct3 == 3'b101), funct3};
        end

        LOAD: begin                 // I-type load (LB LH LW LBU LHU)
            reg_write = 1'b1;
            alu_src = 1'b1;
            mem_read = 1'b1;
            mem_to_reg = 2'b01;   // write back data read from memory
            alu_control = ALU_ADD; // effective address = rs1 + imm
        end

        STORE: begin                // S-type (SB SH SW)
            alu_src = 1'b1;
            mem_write = 1'b1;
            alu_control = ALU_ADD; // effective address = rs1 + imm
        end

        BRANCH: begin               // B-type (BEQ BNE BLT BGE BLTU BGEU)
            branch = 1'b1;
            alu_control = branch_alu_ctrl(funct3);
        end

        JAL_OP: begin               // J-type
            reg_write = 1'b1;
            jal = 1'b1;
            mem_to_reg = 2'b10;    // rd = PC+4 (return address)
        end

        JALR_OP: begin              // I-type (JALR)
            reg_write = 1'b1;
            alu_src = 1'b1;
            jalr = 1'b1;
            mem_to_reg = 2'b10;   // rd = PC+4 (return address)
            alu_control = ALU_ADD; // jump target = rs1 + imm (LSB cleared by datapath)
        end

        LUI_OP: begin               // U-type
            reg_write = 1'b1;
            lui = 1'b1;      // imm_gen already produced u_imm; write directly to rd
        end

        AUIPC_OP: begin             // U-type
            reg_write = 1'b1;
            alu_src = 1'b1;
            alu_a_pc = 1'b1;    // A = PC, B = u_imm → rd = PC + u_imm
            alu_control = ALU_ADD;
        end

        SYSTEM: begin               // ECALL EBREAK — trap handling deferred
        end

        default: begin end          // illegal instruction — all signals remain 0

    endcase
end

endmodule

hdl/imm_gen.sv

// Please refer to RISCV_CARD.pdf on my GitHub for more information about the instruction type formats

module imm_gen (instruction, imm, fmt);

input  logic [31:0] instruction;
output logic [31:0] imm; // immediate value output
output logic [2:0]  fmt; // fmt is used to determine format, 6 formats, so you need 3 bits to essentially choose between them

wire [6:0] opcode = instruction[6:0];
wire sign   = instruction[31];   // sign bit is always inst[31] across all formats

// Immediate assembly (before sign extension), 12b can only reach 2KB, for anything beyond that you need a full 32-bit value. 
// LUI and AUIPC each load the upper 20 bits, and you pair them with an I-type instruction to fill in the lower 12, giving any 32-bit value in two instructions. 

//  I type: 
wire [11:0] i_imm = instruction[31:20];

//  S type: 
wire [11:0] s_imm = {instruction[31:25], instruction[11:7]};

//  B type: 
wire [12:0] b_imm = {instruction[31], instruction[7], instruction[30:25], instruction[11:8], 1'b0};

//  U type:
wire [31:0] u_imm = {instruction[31:12], 12'b0};

//  J type: 
wire [20:0] j_imm = {instruction[31], instruction[19:12], instruction[20], instruction[30:21], 1'b0};

// Format encoding (passed to control unit) 
localparam [2:0] FMT_R = 3'b000;
localparam [2:0] FMT_I = 3'b001;
localparam [2:0] FMT_S = 3'b010;
localparam [2:0] FMT_B = 3'b011;
localparam [2:0] FMT_U = 3'b100;
localparam [2:0] FMT_J = 3'b101;

// opcodes
localparam [6:0] OP = 7'b0110011;  // R: ADD SUB XOR OR AND SLL SRL SRA SLT SLTU
localparam [6:0] OP_IMM = 7'b0010011;  // I: ADDI XORI ORI ANDI SLLI SRLI SRAI SLTI SLTIU
localparam [6:0] LOAD = 7'b0000011;  // I: LB LH LW LBU LHU
localparam [6:0] JALR = 7'b1100111;  // I: JALR
localparam [6:0] SYSTEM = 7'b1110011;  // I: ECALL EBREAK
localparam [6:0] STORE = 7'b0100011;  // S: SB SH SW
localparam [6:0] BRANCH = 7'b1100011;  // B: BEQ BNE BLT BGE BLTU BGEU
localparam [6:0] LUI = 7'b0110111;  // U: LUI
localparam [6:0] AUIPC = 7'b0010111;  // U: AUIPC
localparam [6:0] JAL = 7'b1101111;  // J: JAL

// ── Immediate decode ─────────────────────────────────────────────────────────
always @(*) begin
    imm = 32'b0;
    fmt = FMT_R;

    case (opcode)
        OP: begin                            // R-type no immediate
            fmt = FMT_R;
            imm = 32'b0;
        end

        OP_IMM, LOAD, JALR, SYSTEM: begin   // I-type 12-bit sign-extended
            fmt = FMT_I;
            imm = {{20{sign}}, i_imm};
        end

        STORE: begin                         // S-type 12-bit sign-extended
            fmt = FMT_S;
            imm = {{20{sign}}, s_imm};
        end

        BRANCH: begin                        // B-type 13-bit sign-extended
            fmt = FMT_B;
            imm = {{19{sign}}, b_imm};
        end

        LUI, AUIPC: begin                   // U-type 20-bit upper, no sign extension needed
            fmt = FMT_U;
            imm = u_imm;
        end

        JAL: begin                           // J-type 21-bit sign-extended
            fmt = FMT_J;
            imm = {{11{sign}}, j_imm};
        end

        default: begin
            fmt = FMT_R;
            imm = 32'b0;
        end
    endcase
end

endmodule

hdl/instruction_mem.sv
module instruction_mem(clk, pc, instruction);

parameter instr_length = 32;
parameter pc_length = 32;

input clk;
input [pc_length-1:0] pc;
output [instr_length-1:0] instruction;

reg [31:0] memory [0:1023]; // memory is 32x32 = 1024

initial begin
    $readmemh("program.hex", memory); // read a hex file and load it into memory 
end

assign instruction = memory[pc[11:2]]; // since depth = 1024, 2^10 = 1024, so [11:2] is sufficient 

endmodule

hdl/pc.sv
module pc(pc_in, pc_out, clk, rst);

parameter addr_length = 32; // 32-bit address

input [addr_length-1:0] pc_in; 
output reg [addr_length-1:0] pc_out;  
input clk, rst; 

always @(posedge clk) begin
    if (rst) 
        pc_out <= 32'h00000000; // if reset, reset PC to x0000 
    else 
        pc_out <= pc_in; // program counter out = program counter in at end of cycle
end

endmodule

hdl/top.sv
// Single-cycle RV32I CPU top-level datapath

module top(clk, rst);

input logic clk;
input logic rst;

// PC signals
logic [31:0] pc_out, pc_in, pc_plus4;

// instruction and fields
logic [31:0] instruction;
logic [6:0] opcode;
logic [2:0] funct3;
logic [6:0] funct7;
logic [4:0] rs1, rs2, rd;

// immediate
logic [31:0] imm;
logic [2:0] fmt;

// control signals
logic reg_write;
logic [3:0] alu_control;
logic alu_src;
logic alu_a_pc;
logic lui;
logic mem_read;
logic mem_write;
logic [1:0] mem_to_reg;
logic branch;
logic jal;
logic jalr;
logic [2:0] funct3_out;

// datapath
logic [31:0] rs1_data, rs2_data, write_data;
logic [31:0] alu_a, alu_b, alu_result;
logic alu_zero, alu_overflow, alu_lt, alu_cout;
logic [31:0] mem_read_data;
logic branch_taken;

// instruction field extraction
assign opcode = instruction[6:0];
assign funct3 = instruction[14:12];
assign funct7 = instruction[31:25];
assign rs1 = instruction[19:15];
assign rs2 = instruction[24:20];
assign rd = instruction[11:7];

// PC next logic
assign pc_plus4 = pc_out + 32'd4;
assign branch_taken = branch && (funct3_out[2] ? (alu_result[0] ^ funct3_out[0])
                                               : (alu_zero ^ funct3_out[0]));
assign pc_in = jalr         ? {alu_result[31:1], 1'b0}
             : jal          ? pc_out + imm
             : branch_taken ? pc_out + imm
             :                pc_plus4;

// ALU operand muxes
assign alu_a = alu_a_pc ? pc_out : rs1_data;
assign alu_b = alu_src  ? imm    : rs2_data;

// writeback mux
assign write_data = lui            ? imm
                  : mem_to_reg[1] ? pc_plus4
                  : mem_to_reg[0] ? mem_read_data
                  :                 alu_result;

// module instantiations
pc u_pc (
    .clk(clk), .rst(rst),
    .pc_in(pc_in), .pc_out(pc_out)
);
instruction_mem u_imem (
    .clk(clk), .pc(pc_out), .instruction(instruction)
);
imm_gen u_immgen (
    .instruction(instruction), .imm(imm), .fmt(fmt)
);
control_unit u_ctrl (
    .opcode(opcode), .funct3(funct3), .funct7(funct7),
    .reg_write(reg_write), .alu_control(alu_control),
    .alu_src(alu_src), .alu_a_pc(alu_a_pc), .lui(lui),
    .mem_read(mem_read), .mem_write(mem_write), .mem_to_reg(mem_to_reg),
    .branch(branch), .jal(jal), .jalr(jalr), .funct3_out(funct3_out)
);
reg_file u_regfile (
    .clk(clk), .write_en(reg_write),
    .read_addr1(rs1), .read_addr2(rs2),
    .write_addr(rd), .write_data(write_data),
    .reg1(rs1_data), .reg2(rs2_data)
);
alu u_alu (
    .a(alu_a), .b(alu_b), .ALU_control(alu_control),
    .result(alu_result), .zero(alu_zero),
    .overflow(alu_overflow), .lt(alu_lt), .cout(alu_cout)
);
data_mem u_dmem (
    .clk(clk), .mem_write(mem_write), .mem_read(mem_read),
    .addr(alu_result), .write_data(rs2_data),
    .funct3(funct3_out), .read_data(mem_read_data)
);

endmodule

hdl/tb_top.sv
// Testbench for single-cycle RV32I CPU
// Test program: fibonacci sequence, result fib(8) = 21 ends up in x2

`timescale 1ns/1ps

module tb_top;

reg clk;
reg rst;

top dut (
    .clk(clk),
    .rst(rst)
);

initial clk = 0;
always #5 clk = ~clk;

initial begin
    rst = 1;
    repeat(2) @(posedge clk);
    #1 rst = 0;

    repeat(45) @(posedge clk);

    // x1 = fib(7) = 13, x2 = fib(8) = 21
    if (dut.u_regfile.reg_filex[1] !== 32'd13)
        $display("FAIL x1: got %0d, expected 13", dut.u_regfile.reg_filex[1]);
    if (dut.u_regfile.reg_filex[2] !== 32'd21)
        $display("FAIL x2: got %0d, expected 21", dut.u_regfile.reg_filex[2]);

    $display("simulation done. x1=%0d x2=%0d", dut.u_regfile.reg_filex[1], dut.u_regfile.reg_filex[2]);
    $finish;
end

initial begin
    $dumpfile("tb_top.vcd");
    $dumpvars(0, tb_top);
end

integer cyc;
initial cyc = 0;

always @(posedge clk) begin
    #1;
    cyc = cyc + 1;
    $display("cyc %2d | PC=%08h instr=%08h | x1=%2d x2=%2d x3=%2d x4=%2d",
        cyc,
        dut.pc_out,
        dut.instruction,
        dut.u_regfile.reg_filex[1],
        dut.u_regfile.reg_filex[2],
        dut.u_regfile.reg_filex[3],
        dut.u_regfile.reg_filex[4]
    );
end

endmodule

hdl/tb_top.vcd
$date
	Sat May 30 03:58:18 2026
$end
$version
	Icarus Verilog
$end
$timescale
	1ps
$end
$scope module tb_top $end
$var reg 1 ! clk $end
$var reg 1 " rst $end
$var integer 32 # cyc [31:0] $end
$scope module dut $end
$var wire 1 $ branch_taken $end
$var wire 1 ! clk $end
$var wire 1 " rst $end
$var wire 32 % write_data [31:0] $end
$var wire 32 & rs2_data [31:0] $end
$var wire 5 ' rs2 [4:0] $end
$var wire 32 ( rs1_data [31:0] $end
$var wire 5 ) rs1 [4:0] $end
$var wire 1 * reg_write $end
$var wire 5 + rd [4:0] $end
$var wire 32 , pc_plus4 [31:0] $end
$var wire 32 - pc_out [31:0] $end
$var wire 32 . pc_in [31:0] $end
$var wire 7 / opcode [6:0] $end
$var wire 1 0 mem_write $end
$var wire 2 1 mem_to_reg [1:0] $end
$var wire 32 2 mem_read_data [31:0] $end
$var wire 1 3 mem_read $end
$var wire 1 4 lui $end
$var wire 1 5 jalr $end
$var wire 1 6 jal $end
$var wire 32 7 instruction [31:0] $end
$var wire 32 8 imm [31:0] $end
$var wire 7 9 funct7 [6:0] $end
$var wire 3 : funct3_out [2:0] $end
$var wire 3 ; funct3 [2:0] $end
$var wire 3 < fmt [2:0] $end
$var wire 1 = branch $end
$var wire 1 > alu_zero $end
$var wire 1 ? alu_src $end
$var wire 32 @ alu_result [31:0] $end
$var wire 1 A alu_overflow $end
$var wire 1 B alu_lt $end
$var wire 1 C alu_cout $end
$var wire 4 D alu_control [3:0] $end
$var wire 32 E alu_b [31:0] $end
$var wire 1 F alu_a_pc $end
$var wire 32 G alu_a [31:0] $end
$scope module u_alu $end
$var wire 32 H a [31:0] $end
$var wire 32 I b [31:0] $end
$var wire 1 C cout $end
$var wire 1 A overflow $end
$var wire 1 > zero $end
$var wire 1 B lt $end
$var wire 4 J ALU_control [3:0] $end
$var parameter 4 K ADD $end
$var parameter 4 L AND $end
$var parameter 4 M OR $end
$var parameter 4 N SLL $end
$var parameter 4 O SLT $end
$var parameter 4 P SLTU $end
$var parameter 4 Q SRA $end
$var parameter 4 R SRL $end
$var parameter 4 S SUB $end
$var parameter 4 T XOR $end
$var parameter 32 U data_width $end
$var reg 1 V carry $end
$var reg 32 W result [31:0] $end
$upscope $end
$scope module u_ctrl $end
$var wire 3 X funct3 [2:0] $end
$var wire 7 Y funct7 [6:0] $end
$var wire 7 Z opcode [6:0] $end
$var parameter 4 [ ALU_ADD $end
$var parameter 4 \ ALU_SLT $end
$var parameter 4 ] ALU_SLTU $end
$var parameter 4 ^ ALU_SUB $end
$var parameter 7 _ AUIPC_OP $end
$var parameter 7 ` BRANCH $end
$var parameter 7 a JALR_OP $end
$var parameter 7 b JAL_OP $end
$var parameter 7 c LOAD $end
$var parameter 7 d LUI_OP $end
$var parameter 7 e OP $end
$var parameter 7 f OP_IMM $end
$var parameter 7 g STORE $end
$var parameter 7 h SYSTEM $end
$var reg 1 F alu_a_pc $end
$var reg 4 i alu_control [3:0] $end
$var reg 1 ? alu_src $end
$var reg 1 = branch $end
$var reg 3 j funct3_out [2:0] $end
$var reg 1 6 jal $end
$var reg 1 5 jalr $end
$var reg 1 4 lui $end
$var reg 1 3 mem_read $end
$var reg 2 k mem_to_reg [1:0] $end
$var reg 1 0 mem_write $end
$var reg 1 * reg_write $end
$scope function branch_alu_ctrl $end
$upscope $end
$upscope $end
$scope module u_dmem $end
$var wire 32 l addr [31:0] $end
$var wire 1 ! clk $end
$var wire 3 m funct3 [2:0] $end
$var wire 1 3 mem_read $end
$var wire 1 0 mem_write $end
$var wire 32 n write_data [31:0] $end
$var parameter 32 o DATA_WIDTH $end
$var parameter 32 p MEM_SIZE $end
$var reg 32 q read_data [31:0] $end
$var reg 32 r word [31:0] $end
$upscope $end
$scope module u_imem $end
$var wire 1 ! clk $end
$var wire 32 s instruction [31:0] $end
$var wire 32 t pc [31:0] $end
$var parameter 32 u instr_length $end
$var parameter 32 v pc_length $end
$upscope $end
$scope module u_immgen $end
$var wire 32 w instruction [31:0] $end
$var wire 32 x u_imm [31:0] $end
$var wire 1 y sign $end
$var wire 12 z s_imm [11:0] $end
$var wire 7 { opcode [6:0] $end
$var wire 21 | j_imm [20:0] $end
$var wire 12 } i_imm [11:0] $end
$var wire 13 ~ b_imm [12:0] $end
$var parameter 7 !" AUIPC $end
$var parameter 7 "" BRANCH $end
$var parameter 3 #" FMT_B $end
$var parameter 3 $" FMT_I $end
$var parameter 3 %" FMT_J $end
$var parameter 3 &" FMT_R $end
$var parameter 3 '" FMT_S $end
$var parameter 3 (" FMT_U $end
$var parameter 7 )" JAL $end
$var parameter 7 *" JALR $end
$var parameter 7 +" LOAD $end
$var parameter 7 ," LUI $end
$var parameter 7 -" OP $end
$var parameter 7 ." OP_IMM $end
$var parameter 7 /" STORE $end
$var parameter 7 0" SYSTEM $end
$var reg 3 1" fmt [2:0] $end
$var reg 32 2" imm [31:0] $end
$upscope $end
$scope module u_pc $end
$var wire 1 ! clk $end
$var wire 32 3" pc_in [31:0] $end
$var wire 1 " rst $end
$var parameter 32 4" addr_length $end
$var reg 32 5" pc_out [31:0] $end
$upscope $end
$scope module u_regfile $end
$var wire 1 ! clk $end
$var wire 5 6" read_addr1 [4:0] $end
$var wire 5 7" read_addr2 [4:0] $end
$var wire 32 8" reg1 [31:0] $end
$var wire 32 9" reg2 [31:0] $end
$var wire 5 :" write_addr [4:0] $end
$var wire 32 ;" write_data [31:0] $end
$var wire 1 * write_en $end
$var parameter 32 <" addr_bits $end
$var parameter 32 =" depth $end
$var parameter 32 >" width $end
$var integer 32 ?" i [31:0] $end
$upscope $end
$upscope $end
$upscope $end
$enddefinitions $end
$comment Show the parameter values. $end
$dumpall
b100000 >"
b100000 ="
b101 <"
b100000 4"
b1110011 0"
b100011 /"
b10011 ."
b110011 -"
b110111 ,"
b11 +"
b1100111 *"
b1101111 )"
b100 ("
b10 '"
b0 &"
b101 %"
b1 $"
b11 #"
b1100011 ""
b10111 !"
b100000 v
b100000 u
b10000000000 p
b100000 o
b1110011 h
b100011 g
b10011 f
b110011 e
b110111 d
b11 c
b1101111 b
b1100111 a
b1100011 `
b10111 _
b1000 ^
b11 ]
b10 \
b0 [
b100000 U
b100 T
b1000 S
b101 R
b1101 Q
b11 P
b10 O
b1 N
b110 M
b111 L
b0 K
$end
#0
$dumpvars
b100000 ?"
bx ;"
bx :"
bx 9"
bx 8"
bx 7"
bx 6"
bx 5"
bx 3"
b0 2"
b0 1"
bx0 ~
bx }
bx0 |
bx {
bx z
xy
bx000000000000 x
bx w
bx t
bx s
bx r
bx q
bx n
bx m
bx l
bx k
bx j
bx i
bx Z
bx Y
bx X
bx W
xV
bx J
bx I
bx H
bx G
xF
bx E
bx D
xC
xB
xA
bx @
x?
x>
x=
b0 <
bx ;
bx :
bx 9
b0 8
bx 7
x6
x5
x4
x3
bx 2
bx 1
x0
bx /
bx .
bx -
bx ,
bx +
x*
bx )
bx (
bx '
bx &
bx %
x$
b0 #
1"
0!
$end
#5000
0A
b0 %
b0 ;"
0$
b0 2
b0 q
0C
0V
1>
b0 @
b0 W
b0 l
b1 <
b1 1"
0B
b0 E
b0 I
b0 G
b0 H
b0 :
b0 j
b0 m
05
06
0=
b0 1
b0 k
00
03
04
0F
1?
b0 D
b0 J
b0 i
1*
b10011 {
0y
b0 }
b1 z
b100000000000 ~
b0 x
b0 |
b1 +
b1 :"
b0 &
b0 n
b0 9"
b0 '
b0 7"
b0 (
b0 8"
b0 )
b0 6"
b0 9
b0 Y
b0 ;
b0 X
b10011 /
b10011 Z
b100 .
b100 3"
b10010011 7
b10010011 s
b10010011 w
b100 ,
b0 -
b0 t
b0 5"
1!
#6000
b1 #
#10000
0!
#15000
1!
#16000
0"
b10 #
#20000
0!
#25000
b1 %
b1 ;"
0>
b1 @
b1 W
b1 l
1B
b1 E
b1 I
b1 8
b1 2"
b1 <
b1 1"
b1000 .
b1000 3"
b1 }
b10 z
b10 ~
b100000000000000000000 x
b100000000000 |
b10 +
b10 :"
b1 '
b1 7"
b100000000000100010011 7
b100000000000100010011 s
b100000000000100010011 w
b1000 ,
b100 -
b100 t
b100 5"
1!
#26000
b11 #
#30000
0!
#35000
b111 %
b111 ;"
0>
b111 @
b111 W
b111 l
b111 E
b111 I
b1 <
b1 1"
b111 8
b111 2"
b1100 .
b1100 3"
b111 }
b11 z
b100000000010 ~
b11100000000000000000000 x
b100000000110 |
b11 +
b11 :"
b111 '
b111 7"
b11100000000000110010011 7
b11100000000000110010011 s
b11100000000000110010011 w
b1100 ,
b1000 -
b1000 t
b1000 5"
1!
#36000
b100 #
#40000
0!
#45000
b1 %
b1 ;"
0>
b1 @
b1 W
b1 l
b1 E
b1 I
b0 <
b0 1"
b0 8
b0 2"
0?
1*
b10000 .
b10000 3"
b110011 {
b10 }
b100 z
b100 ~
b1000001000000000000000 x
b1000000000000010 |
b100 +
b100 :"
b1 &
b1 n
b1 9"
b10 '
b10 7"
b1 )
b1 6"
b110011 /
b110011 Z
b1000001000001000110011 7
b1000001000001000110011 s
b1000001000001000110011 w
b10000 ,
b1100 -
b1100 t
b1100 5"
1!
#46000
b101 #
#50000
0!
#55000
0>
b1 @
b1 W
b1 l
b0 E
b0 I
0B
b1 G
b1 H
b10100 .
b10100 3"
b0 }
b1 z
b100000000000 ~
b10000000000000000 x
b10000000000000000 |
b1 +
b1 :"
b0 &
b0 n
b0 9"
b0 '
b0 7"
b1 (
b1 8"
b10 )
b10 6"
b10000000010110011 7
b10000000010110011 s
b10000000010110011 w
b10100 ,
b10000 -
b10000 t
b10000 5"
1!
#56000
b110 #
#60000
0!
#65000
b11000 .
b11000 3"
b10 z
b10 ~
b100000000000000000 x
b100000000000000000 |
b10 +
b10 :"
b100 )
b100 6"
b100000000100110011 7
b100000000100110011 s
b100000000100110011 w
b11000 ,
b10100 -
b10100 t
b10100 5"
1!
#66000
b111 #
#70000
0!
#75000
b110 %
b110 ;"
1C
1V
0>
b110 @
b110 W
b110 l
b11111111111111111111111111111111 E
b11111111111111111111111111111111 I
b11111111111111111111111111111111 8
b11111111111111111111111111111111 2"
b1 <
b1 1"
b111 G
b111 H
1?
1*
b11100 .
b11100 3"
b10011 {
1y
b111111111111 }
b111111100011 z
b1111111100010 ~
b11111111111100011000000000000000 x
b100011000111111111110 |
b11 +
b11 :"
b11111 '
b11111 7"
b111 (
b111 8"
b11 )
b11 6"
b1111111 9
b1111111 Y
b10011 /
b10011 Z
b11111111111100011000000110010011 7
b11111111111100011000000110010011 s
b11111111111100011000000110010011 w
b11100 ,
b11000 -
b11000 t
b11000 5"
1!
#76000
b1000 #
#80000
0!
